{
  "testnet": {
    "version": "0.1.3",
    "force": false,
    "newFeature": "Add automatic backup function.",
    "optimization": "Fix the problem of invoice transactions in channels under Lightning Network.",
    "url": "https://github.com/omnilaboratory/OBAndroid/releases/download/v0.1.3-testnet/OBAndroid_testnet_v0.1.3.apk"
  },
  "regtest": {
    "version": "0.1.0",
    "force": false,
    "newFeature": "First publish",
    "optimization": "Not yet",
    "url": "https://github.com/omnilaboratory/OBAndroid/releases/download/v0.1.0-testnet/OBAndroid_testnet_0.1.0_beta.10_release.apk"
  },
  "mainnet": {
    "version": "0.1.3",
    "force": false,
    "newFeature": "Add automatic backup function.",
    "optimization": "Fix the problem of invoice transactions in channels under Lightning Network.",
    "url": "https://github.com/omnilaboratory/OBAndroid/releases/download/v0.1.3-mainnet/OBAndroid_mainnet_v0.1.3.apk"
  }
}